Workbook
Name Variance: Sheet1!$A$1:$A$2

Sheet Budgetierte und Ist-Kosten
A2: Hype Sneakers hat die folgenden Kategorien mit variablen Kosten:
A3: Budgetierte Ergebnisse für 2019
B5: Direkte Materialkosten | C5: Lederpreis pro m2 | D5: Benötigtes Leder für ein Paar Turnschuhe in m2
C6: 40 | D6: 1
B8: Direkte Fertigungsarbeit | C8: Fertigungskosten pro Einheit
C9: 25
B11: Maschinenstunden | C11: Kostenrate pro Maschinenstunde | D11: Maschinenstunden pro Einheit
B12: =C15*D12 -> 10000 | C12: 15 | D12: 1
B14: Budgetiert für 2019
B15: Einheiten zur Herstellung und zum Verkauf | C15: 10000
B16: Direkte Materialkosten | C16: =C6 -> 40
B17: Direkte Fertigungskosten | C17: =C9 -> 25
B18: Variable Fertigungsgemeinkosten | C18: =C12 -> 15
B19: Summe variable Kosten | C19: =SUM(C16:C18) -> 80
B20: Summe Fixkosten | C20: 120000
B21: Geplanter Verkaufspreis pro Paar Turnschuhe | C21: 140
A24: Ist-Ergebnisse für 2019
B26: Direkte Materialkosten | C26: Lederpreis pro m2 | D26: Benötigtes Leder für ein Paar Turnschuhe in m2
C27: 50 | D27: 1.2
B29: Direkte Fertigungsarbeit (Leder) | C29: Fertigungskosten pro Einheit
C30: 25
B32: Maschinenstunden | C32: Kostenrate pro Maschinenstunde | D32: Maschinenstunden pro Einheit
B33: =C36*D33 -> 10800 | C33: =C39/B33 -> 22 | D33: 0.9
B35: Ist-Ergebnisse für 2019
B36: Einheiten zur Herstellung und zum Verkauf | C36: 12000
B37: Summe direkte Materialkosten | C37: =C27*D27*C36 -> 720000
B38: Summe direkte Fertigungskosten | C38: =C30*C36 -> 300000
B39: Summe variable Fertigungsgemeinkosten | C39: 237600
B40: Summe variable Kosten | C40: =SUM(C37:C39) -> 1257600
B41: Summe Fixkosten | C41: 100000
B42: Geplanter Verkaufspreis pro Paar Turnschuhe | C42: 150

Sheet LEVEL 1-3 Analyse
A2: Erstellen Sie einen Leistungsbericht, der ein flexibles Budget und ein statisches Budget verwendet.
A4: LEVEL 1 | B4: Ist-Ergebnis (1) | C4: Statische Budgetabweichung | K4: Statisches Budget (2)
A5: Verkaufte Einheiten | B5: ='Budgetierte und Ist-Kosten'!C36 -> 12000 | C5: =B5-K5 -> 2000 | J5: G | K5: ='Budgetierte und Ist-Kosten'!C15 -> 10000
A6: Erlöse | B6: ='Budgetierte und Ist-Kosten'!C36*'Budgetierte und Ist-Kosten'!C42 -> 1800000 | C6: =B6-K6 -> 400000 | J6: G | K6: ='Budgetierte und Ist-Kosten'!C21*'Budgetierte und Ist-Kosten'!C15 -> 1400000
A7: Direkte Materialkosten | B7: ='Budgetierte und Ist-Kosten'!C37 -> 720000 | C7: =B7-K7 -> 320000 | J7: U | K7: ='Budgetierte und Ist-Kosten'!C16*'Budgetierte und Ist-Kosten'!C15 -> 400000
A8: Direkte Fertigungskosten | B8: ='Budgetierte und Ist-Kosten'!C38 -> 300000 | C8: =B8-K8 -> 50000 | J8: U | K8: ='Budgetierte und Ist-Kosten'!C17*'Budgetierte und Ist-Kosten'!C15 -> 250000
A9: Variable Fertigungsgemeinkosten | B9: ='Budgetierte und Ist-Kosten'!C39 -> 237600 | C9: =B9-K9 -> 87600 | J9: U | K9: ='Budgetierte und Ist-Kosten'!B12*'Budgetierte und Ist-Kosten'!C12 -> 150000
A10: Summe variable Kosten | B10: =SUM(B7:B9) -> 1257600 | C10: =B10-K10 -> 457600 | J10: U | K10: =SUM(K7:K9) -> 800000
A11: Deckungsbeitrag | B11: ='LEVEL 1-3 Analyse'!B6-'LEVEL 1-3 Analyse'!B10 -> 542400 | C11: =B11-K11 -> -57600 | J11: U | K11: =K6-K10 -> 600000
A12: Fixkosten | B12: ='Budgetierte und Ist-Kosten'!C41 -> 100000 | C12: =B12-K12 -> -20000 | J12: G | K12: ='Budgetierte und Ist-Kosten'!C20 -> 120000
A13: Betriebsergebnis | B13: =B11-B12 -> 442400 | C13: =B13-K13 -> -37600 | J13: U | K13: =K11-K12 -> 480000
A20: LEVEL 2 | B20: Ist-Ergebnis (1) | C20: Flexible Budgetabweichung (1 - 3) | H20: Flexibles Budget (3) | I20: Absatzvolumenabweichung (3 - 2) | K20: Statisches Budget (2)
A21: Verkaufte Einheiten | B21: ='Budgetierte und Ist-Kosten'!C36 -> 12000 | C21: =B21-H21 -> 0 | H21: ='Budgetierte und Ist-Kosten'!C36 -> 12000 | I21: =H21-K21 -> 2000 | J21: G | K21: ='Budgetierte und Ist-Kosten'!C15 -> 10000
A22: Erlöse | B22: ='Budgetierte und Ist-Kosten'!C36*'Budgetierte und Ist-Kosten'!C42 -> 1800000 | C22: =B22-H22 -> 120000 | G22: G | H22: ='Budgetierte und Ist-Kosten'!C36*'Budgetierte und Ist-Kosten'!C21 -> 1680000 | I22: =H22-K22 -> 280000 | J22: U | K22: ='Budgetierte und Ist-Kosten'!C15*'Budgetierte und Ist-Kosten'!C21 -> 1400000
A23: Direkte Materialkosten | B23: ='Budgetierte und Ist-Kosten'!C36*'Budgetierte und Ist-Kosten'!C27*'Budgetierte und Ist-Kosten'!D27 -> 720000 | C23: =B23-H23 -> 240000 | G23: U | H23: ='Budgetierte und Ist-Kosten'!C36*'Budgetierte und Ist-Kosten'!C16 -> 480000 | I23: =H23-K23 -> 80000 | J23: U | K23: ='Budgetierte und Ist-Kosten'!C15*'Budgetierte und Ist-Kosten'!C16 -> 400000
A24: Direkte Fertigungskosten | B24: ='Budgetierte und Ist-Kosten'!C36*'Budgetierte und Ist-Kosten'!C30 -> 300000 | C24: =B24-H24 -> 0 | H24: ='Budgetierte und Ist-Kosten'!C36*'Budgetierte und Ist-Kosten'!C17 -> 300000 | I24: =H24-K24 -> 50000 | J24: U | K24: ='Budgetierte und Ist-Kosten'!C15*'Budgetierte und Ist-Kosten'!C17 -> 250000
A25: Variable Fertigungsgemeinkosten | B25: ='Budgetierte und Ist-Kosten'!C39 -> 237600 | C25: =B25-H25 -> 57600 | G25: U | H25: ='Budgetierte und Ist-Kosten'!C36*'Budgetierte und Ist-Kosten'!D12*'Budgetierte und Ist-Kosten'!C12 -> 180000 | I25: =H25-K25 -> 30000 | J25: U | K25: ='Budgetierte und Ist-Kosten'!B12*'Budgetierte und Ist-Kosten'!C12 -> 150000
A26: Summe variable Kosten | B26: =SUM(B23:B25) -> 1257600 | C26: =B26-H26 -> 297600 | G26: U | H26: =SUM(H23:H25) -> 960000 | I26: =H26-K26 -> 160000 | J26: U | K26: =SUM(K23:K25) -> 800000
A27: Deckungsbeitrag | B27: =B22-B26 -> 542400 | C27: =B27-H27 -> -177600 | G27: U | H27: =H22-H26 -> 720000 | I27: =H27-K27 -> 120000 | K27: =K22-K26 -> 600000
A28: Fixkosten | B28: ='Budgetierte und Ist-Kosten'!C41 -> 100000 | C28: =B28-H28 -> -20000 | G28: G | H28: ='Budgetierte und Ist-Kosten'!C20 -> 120000 | I28: 0 | K28: ='Budgetierte und Ist-Kosten'!C20 -> 120000
A29: Betriebsergebnis | B29: =B27-B28 -> 442400 | C29: =B29-H29 -> -157600 | G29: U | H29: =H27-H28 -> 600000 | I29: =H29-K29 -> 120000 | J29: G | K29: =K27-K28 -> 480000
A36: LEVEL 3 | B36: Ist-Ergebnis (1) | C36: Preisabweichung (1 - 4) | E36: Flexibler Budget - Input (4) | F36: Effizienzabweichung (4 - 3) | H36: Flexibles Budget (3) | I36: Absatzvolumenabweichung (3 - 2) | K36: Statisches Budget (2)
A37: Verkaufte Einheiten | B37: ='Budgetierte und Ist-Kosten'!C36 -> 12000 | C37: =B37-E37 -> 0 | E37: ='Budgetierte und Ist-Kosten'!C36 -> 12000 | F37: =E37-H37 -> 0 | G37: G | H37: ='Budgetierte und Ist-Kosten'!C36 -> 12000 | I37: =H37-K37 -> 2000 | J37: G | K37: ='Budgetierte und Ist-Kosten'!C15 -> 10000
A38: Erlöse | B38: ='Budgetierte und Ist-Kosten'!C36*'Budgetierte und Ist-Kosten'!C42 -> 1800000 | C38: =B38-E38 -> 120000 | D38: G | E38: ='Budgetierte und Ist-Kosten'!C36*'Budgetierte und Ist-Kosten'!C21 -> 1680000 | F38: =E38-H38 -> 0 | G38: G | H38: ='Budgetierte und Ist-Kosten'!C36*'Budgetierte und Ist-Kosten'!C21 -> 1680000 | I38: =H38-K38 -> 280000 | J38: U | K38: ='Budgetierte und Ist-Kosten'!C15*'Budgetierte und Ist-Kosten'!C21 -> 1400000
A39: Direkte Materialkosten | B39: ='Budgetierte und Ist-Kosten'!C37 -> 720000 | C39: =B39-E39 -> 144000 | D39: U | E39: ='Budgetierte und Ist-Kosten'!C36*'Budgetierte und Ist-Kosten'!C16*'Budgetierte und Ist-Kosten'!D27 -> 576000 | F39: =E39-H39 -> 96000 | G39: U | H39: ='Budgetierte und Ist-Kosten'!C36*'Budgetierte und Ist-Kosten'!C16 -> 480000 | I39: =H39-K39 -> 80000 | J39: U | K39: ='Budgetierte und Ist-Kosten'!C15*'Budgetierte und Ist-Kosten'!C16 -> 400000
A40: Direkte Fertigungskosten | B40: ='Budgetierte und Ist-Kosten'!C38 -> 300000 | C40: =B40-E40 -> 0 | E40: ='Budgetierte und Ist-Kosten'!C36*'Budgetierte und Ist-Kosten'!C30 -> 300000 | F40: =E40-H40 -> 0 | G40: U | H40: ='Budgetierte und Ist-Kosten'!C36*'Budgetierte und Ist-Kosten'!C17 -> 300000 | I40: =H40-K40 -> 50000 | J40: U | K40: ='Budgetierte und Ist-Kosten'!C15*'Budgetierte und Ist-Kosten'!C17 -> 250000
A41: Variable Fertigungsgemeinkosten | B41: ='Budgetierte und Ist-Kosten'!C39 -> 237600 | C41: =B41-E41 -> 75600 | D41: U | E41: ='Budgetierte und Ist-Kosten'!C36*'Budgetierte und Ist-Kosten'!C12*'Budgetierte und Ist-Kosten'!D33 -> 162000 | F41: =E41-H41 -> -18000 | G41: G | H41: ='Budgetierte und Ist-Kosten'!C36*'Budgetierte und Ist-Kosten'!C12*'Budgetierte und Ist-Kosten'!D12 -> 180000 | I41: =H41-K41 -> 30000 | J41: U | K41: ='Budgetierte und Ist-Kosten'!B12*'Budgetierte und Ist-Kosten'!C12 -> 150000
A42: Summe variable Kosten | B42: =SUM(B39:B41) -> 1257600 | C42: =B42-E42 -> 219600 | D42: U | E42: =SUM(E39:E41) -> 1038000 | F42: =E42-H42 -> 78000 | G42: U | H42: =SUM(H39:H41) -> 960000 | I42: =H42-K42 -> 160000 | J42: U | K42: =SUM(K39:K41) -> 800000
A43: Deckungsbeitrag | B43: =B38-B42 -> 542400 | C43: =B43-E43 -> -99600 | D43: U | E43: =E38-E42 -> 642000 | F43: =E43-H43 -> -78000 | G43: U | H43: =H38-H42 -> 720000 | I43: =H43-K43 -> 120000 | J43: U | K43: =K38-K42 -> 600000
A44: Fixkosten | B44: ='Budgetierte und Ist-Kosten'!C41 -> 100000 | C44: =B44-E44 -> -20000 | D44: G | E44: ='Budgetierte und Ist-Kosten'!C20 -> 120000 | F44: - | H44: ='Budgetierte und Ist-Kosten'!C20 -> 120000 | I44: 0 | K44: ='Budgetierte und Ist-Kosten'!C20 -> 120000
A45: Betriebsergebnis | B45: =B43-B44 -> 442400 | C45: =B45-E45 -> -79600 | D45: U | E45: =E43-E44 -> 522000 | F45: =E45-H45 -> -78000 | G45: U | H45: =H43-H44 -> 600000 | I45: =H45-K45 -> 120000 | J45: G | K45: =K43-K44 -> 480000

Sheet Sheet1
A1: F
A2: U
